conceptnet_local/__init__.py
conceptnet_local/_a_star.py
conceptnet_local/_a_star_variants.py
conceptnet_local/_cn_service.py
conceptnet_local/_concept_extraction.py
conceptnet_local/_utils.py
conceptnet_local/_yen_greedy.py
conceptnet_local-1.0.3.dist-info/LICENSE
conceptnet_local-1.0.3.dist-info/METADATA
conceptnet_local-1.0.3.dist-info/WHEEL
conceptnet_local-1.0.3.dist-info/top_level.txt
conceptnet_local-1.0.3.dist-info/RECORD
