Metadata-Version: 2.2
Name: conceptnet_local
Version: 1.0.3
Summary: ConceptNet and embeddings with a local DB and API.
Author-email: Lukas Mautner <lukas.mautner98@gmail.com>
Project-URL: Homepage, https://github.com/lukDev/conceptnet-local
Classifier: Programming Language :: Python :: 3
Classifier: License :: OSI Approved :: MIT License
Classifier: Operating System :: OS Independent
Requires-Python: >=3.12
License-File: LICENSE
Requires-Dist: numpy
Requires-Dist: pydantic
Requires-Dist: sortedcontainers
Requires-Dist: python-dotenv
Requires-Dist: inflect
Requires-Dist: nltk
Provides-Extra: dev
Requires-Dist: black; extra == "dev"
